{
 "allow_comments": 0,
 "allow_delete": 0,
 "allow_edit": 0,
 "allow_incomplete": 0,
 "allow_multiple": 0,
 "allow_print": 0,
 "anonymous": 0,
 "apply_document_permissions": 0,
 "button_label": "Save",
 "condition_json": "[]",
 "creation": "2025-02-21 11:58:10.017986",
 "doc_type": "Student",
 "docstatus": 0,
 "doctype": "Web Form",
 "idx": 0,
 "introduction_text": "<div class=\"ql-editor read-mode\"><p>This is Student Report Card</p></div>",
 "is_standard": 1,
 "list_columns": [],
 "login_required": 0,
 "max_attachment_size": 0,
 "modified": "2025-03-06 15:17:58.761103",
 "modified_by": "Administrator",
 "module": "Programming",
 "name": "student-report-form",
 "owner": "Administrator",
 "published": 0,
 "route": "student-report-form",
 "show_attachments": 0,
 "show_list": 0,
 "show_sidebar": 0,
 "title": "Student Report Form",
 "web_form_fields": [
  {
   "allow_read_on_all_link_options": 0,
   "fieldname": "section_break_ebyi",
   "fieldtype": "Section Break",
   "hidden": 0,
   "label": "Student Personal Details",
   "max_length": 0,
   "max_value": 0,
   "precision": "",
   "read_only": 0,
   "reqd": 0,
   "show_in_filter": 0
  },
  {
   "allow_read_on_all_link_options": 0,
   "fieldname": "std_id",
   "fieldtype": "Int",
   "hidden": 0,
   "label": "std_id",
   "max_length": 0,
   "max_value": 0,
   "precision": "",
   "read_only": 0,
   "reqd": 1,
   "show_in_filter": 0
  },
  {
   "allow_read_on_all_link_options": 0,
   "fieldname": "std_name",
   "fieldtype": "Data",
   "hidden": 0,
   "label": "std_name",
   "max_length": 0,
   "max_value": 0,
   "precision": "",
   "read_only": 0,
   "reqd": 1,
   "show_in_filter": 0
  },
  {
   "allow_read_on_all_link_options": 0,
   "fieldname": "column_break_4bgb",
   "fieldtype": "Column Break",
   "hidden": 0,
   "max_length": 0,
   "max_value": 0,
   "precision": "",
   "read_only": 0,
   "reqd": 0,
   "show_in_filter": 0
  },
  {
   "allow_read_on_all_link_options": 0,
   "fieldname": "dob",
   "fieldtype": "Date",
   "hidden": 0,
   "label": "DOB",
   "max_length": 0,
   "max_value": 0,
   "precision": "",
   "read_only": 0,
   "reqd": 1,
   "show_in_filter": 0
  },
  {
   "allow_read_on_all_link_options": 0,
   "default": "",
   "fieldname": "gender",
   "fieldtype": "Link",
   "hidden": 0,
   "label": "Gender",
   "max_length": 0,
   "max_value": 0,
   "options": "Gender",
   "precision": "",
   "read_only": 0,
   "reqd": 1,
   "show_in_filter": 0
  },
  {
   "allow_read_on_all_link_options": 0,
   "fieldname": "student_educational_details_section",
   "fieldtype": "Section Break",
   "hidden": 0,
   "label": "Student Educational Details",
   "max_length": 0,
   "max_value": 0,
   "precision": "",
   "read_only": 0,
   "reqd": 0,
   "show_in_filter": 0
  },
  {
   "allow_read_on_all_link_options": 0,
   "fieldname": "en_roll_date",
   "fieldtype": "Date",
   "hidden": 0,
   "label": "En. Roll. Date",
   "max_length": 0,
   "max_value": 0,
   "precision": "",
   "read_only": 0,
   "reqd": 1,
   "show_in_filter": 0
  },
  {
   "allow_read_on_all_link_options": 0,
   "fieldname": "subjects",
   "fieldtype": "Table",
   "hidden": 0,
   "label": "Subjects",
   "max_length": 0,
   "max_value": 0,
   "options": "Subjects",
   "precision": "",
   "read_only": 0,
   "reqd": 0,
   "show_in_filter": 0
  },
  {
   "allow_read_on_all_link_options": 0,
   "fieldname": "column_break_gqwd",
   "fieldtype": "Column Break",
   "hidden": 0,
   "max_length": 0,
   "max_value": 0,
   "precision": "",
   "read_only": 0,
   "reqd": 0,
   "show_in_filter": 0
  },
  {
   "allow_read_on_all_link_options": 0,
   "fieldname": "grade",
   "fieldtype": "Data",
   "hidden": 0,
   "label": "Grade",
   "max_length": 0,
   "max_value": 0,
   "precision": "",
   "read_only": 0,
   "reqd": 1,
   "show_in_filter": 0
  },
  {
   "allow_read_on_all_link_options": 0,
   "fieldname": "status",
   "fieldtype": "Select",
   "hidden": 0,
   "label": "Status",
   "max_length": 0,
   "max_value": 0,
   "options": "Failed\nPass\nExcellent",
   "precision": "",
   "read_only": 1,
   "reqd": 0,
   "show_in_filter": 0
  }
 ]
}